pyanthem/__init__.py
pyanthem/decompmp4.py
pyanthem/obsolete.py
pyanthem/pyanthem.py
pyanthem/pyanthem_vars.py
pyanthem-1.2.0.dist-info/LICENSE
pyanthem-1.2.0.dist-info/METADATA
pyanthem-1.2.0.dist-info/WHEEL
pyanthem-1.2.0.dist-info/top_level.txt
pyanthem-1.2.0.dist-info/RECORD
