Metadata-Version: 2.1
Name: pyanthem
Version: 1.2.0
Summary: pyanthem - an audiovisualization tool to make your data more interesting
Home-page: https://github.com/nicthib/pyanthem
Author: Nic Thibodeaux
Author-email: dnt2111@columbia.edu
Classifier: Programming Language :: Python :: 3
Classifier: License :: OSI Approved :: MIT License
Classifier: Operating System :: OS Independent
Requires-Python: >=3.7
License-File: LICENSE
Requires-Dist: midiutil
Requires-Dist: matplotlib
Requires-Dist: pygame
Requires-Dist: sklearn
Requires-Dist: requests
Requires-Dist: gdown
Requires-Dist: pillow
Requires-Dist: mido
Requires-Dist: ttkthemes
Requires-Dist: h5py
Requires-Dist: scipy
Requires-Dist: scikit-learn
Requires-Dist: numpy
